fivepyfive/__init__.py
fivepyfive/__main__.py
fivepyfive/app.py
fivepyfive/fivepyfive.css
fivepyfive/game_cell.py
fivepyfive/game_grid.py
fivepyfive/game_header.py
fivepyfive/game_screen.py
fivepyfive/help.md
fivepyfive/help_screen.py
fivepyfive/py.typed
fivepyfive/winner.py
fivepyfive-0.2.0.dist-info/LICENSE
fivepyfive-0.2.0.dist-info/METADATA
fivepyfive-0.2.0.dist-info/WHEEL
fivepyfive-0.2.0.dist-info/entry_points.txt
fivepyfive-0.2.0.dist-info/top_level.txt
fivepyfive-0.2.0.dist-info/RECORD
