Metadata-Version: 2.1
Name: fivepyfive
Version: 0.2.0
Summary: A little annoying puzzle for the terminal.
Home-page: https://github.com/davep/fivepyfive
Author: Dave Pearson
Author-email: davep@davep.org
Maintainer: Dave Pearson
Maintainer-email: davep@davep.org
License: License :: OSI Approved :: GNU General Public License v3 or later (GPLv3+)
Keywords: puzzle game terminal
Classifier: License :: OSI Approved :: GNU General Public License v3 or later (GPLv3+)
Classifier: Environment :: Console
Classifier: Development Status :: 3 - Alpha
Classifier: Intended Audience :: End Users/Desktop
Classifier: Operating System :: OS Independent
Classifier: Programming Language :: Python :: 3.8
Classifier: Programming Language :: Python :: 3.9
Classifier: Programming Language :: Python :: 3.10
Classifier: Programming Language :: Python :: 3.11
Classifier: Topic :: Terminals
Classifier: Topic :: Games/Entertainment :: Puzzle Games
Classifier: Typing :: Typed
Requires-Python: >=3.8
License-File: LICENSE
Requires-Dist: textual (==0.11.1)
